MongoAgent/__init__.py
MongoAgent/core.py
mongoagent-0.1.2.dist-info/METADATA
mongoagent-0.1.2.dist-info/WHEEL
mongoagent-0.1.2.dist-info/top_level.txt
mongoagent-0.1.2.dist-info/RECORD
