Metadata-Version: 2.4
Name: MongoAgent
Version: 0.1.2
Summary: An Applicaiton help to communicate with mongo using chatgpt and AI
Author: Drjslab
Classifier: Programming Language :: Python :: 3
Classifier: License :: OSI Approved :: MIT License
Requires-Python: >=3.6
Requires-Dist: pymongo
Dynamic: author
Dynamic: classifier
Dynamic: description
Dynamic: description-content-type
Dynamic: requires-dist
Dynamic: requires-python
Dynamic: summary
